{"image_h": 313, "image_w": 733, "seat_h": 22, "seat_w": 36, "seats": [{"x": 29, "y": 48, "list": [1]}, {"x": 29, "y": 72, "list": [1]}, {"x": 29, "y": 97, "list": [2]}, {"x": 29, "y": 121, "list": [1]}, {"x": 29, "y": 146, "list": [1]}, {"x": 29, "y": 187, "list": [2]}, {"x": 29, "y": 212, "list": [1]}, {"x": 29, "y": 236, "list": [1]}, {"x": 29, "y": 261, "list": [1]}, {"x": 29, "y": 285, "list": [1]}, {"x": 93, "y": 0, "list": [2, 1]}, {"x": 93, "y": 24, "list": [1, 1]}, {"x": 93, "y": 48, "list": [1, 2]}, {"x": 93, "y": 73, "list": [2, 1]}, {"x": 93, "y": 97, "list": [1, 2]}, {"x": 93, "y": 121, "list": [2, 1]}, {"x": 93, "y": 146, "list": [2, 2]}, {"x": 93, "y": 195, "list": [2, 1]}, {"x": 93, "y": 236, "list": [2, 0]}, {"x": 93, "y": 261, "list": [2, 0]}, {"x": 194, "y": 0, "list": [0, 1, 0, 1, 1]}, {"x": 194, "y": 24, "list": [2, 2, 0, 2, 2]}, {"x": 194, "y": 48, "list": [1, 2, 0, 2, 1]}, {"x": 194, "y": 73, "list": [2, 2, 0, 1, 1]}, {"x": 194, "y": 97, "list": [1, 1, 0, 1, 2]}, {"x": 194, "y": 121, "list": [1, 1, 0, 1, 2]}, {"x": 194, "y": 146, "list": [0, 0, 0, 2, 1]}, {"x": 194, "y": 171, "list": [1, 2, 0, 1, 1]}, {"x": 194, "y": 195, "list": [2, 2, 0, 1, 2]}, {"x": 194, "y": 260, "list": [2, 2, 2, 1, 2]}, {"x": 194, "y": 285, "list": [2, 2, 1, 2, 1]}, {"x": 423, "y": 0, "list": [2, 2, 1, 2, 2, 2, 0]}, {"x": 423, "y": 48, "list": [2, 2, 2, 2, 1, 1, 1]}, {"x": 423, "y": 72, "list": [2, 1, 1, 2, 1, 1, 2]}, {"x": 423, "y": 121, "list": [0, 0, 1, 1, 0, 0, 0]}, {"x": 423, "y": 146, "list": [0, 0, 1, 1, 0, 0, 2]}, {"x": 423, "y": 195, "list": [0, 1, 1, 2, 2, 2, 2]}, {"x": 423, "y": 219, "list": [0, 2, 2, 1, 1, 2, 0]}, {"x": 423, "y": 261, "list": [0, 1, 1, 1, 2, 2, 0]}, {"x": 423, "y": 285, "list": [0, 2, 2, 1, 1, 1, 2]}]}